src/create_co.py
src/test.py
co_automation_lib-0.1.0.dist-info/METADATA
co_automation_lib-0.1.0.dist-info/WHEEL
co_automation_lib-0.1.0.dist-info/top_level.txt
co_automation_lib-0.1.0.dist-info/RECORD
